SHiNiNG/__init__.py
SHiNiNG/__version__.py
SHiNiNG/rand.py
SHiNiNG/models/__init__.py
SHiNiNG/models/word2vec_mlp.py
SHiNiNG/tokenizer/__init__.py
SHiNiNG/tokenizer/n_gram_gen.py
SHiNiNG/tokenizer/tokenize.py
SHiNiNG-0.0.1.0.dist-info/METADATA
SHiNiNG-0.0.1.0.dist-info/RECORD
SHiNiNG-0.0.1.0.dist-info/WHEEL
SHiNiNG-0.0.1.0.dist-info/top_level.txt
