Metadata-Version: 2.1
Name: SHiNiNG
Version: 0.0.1.0
Summary: The easiest and powerful deep-learning-text-classifier based on keras and gensim for human beings and all purposes.
Home-page: https://github.com/eathoublu/SHiNiNG
Author: Lan-Yixiao_Eathoublu
Author-email: 1012950361@qq.com
License: MIT
Platform: UNKNOWN
Classifier: License :: OSI Approved :: MIT License
Classifier: Programming Language :: Python
Classifier: Programming Language :: Python :: 3
Classifier: Programming Language :: Python :: 3.6
Classifier: Programming Language :: Python :: Implementation :: CPython
Classifier: Programming Language :: Python :: Implementation :: PyPy
Requires-Python: >=3.6.0
Provides-Extra: fancy feature
Requires-Dist: keras
Requires-Dist: jieba
Requires-Dist: gensim
Requires-Dist: tensorflow
Requires-Dist: numpy
Provides-Extra: fancy feature
Requires-Dist: tqdm; extra == 'fancy feature'
